eratos/__init__.py
eratos/adapter.py
eratos/climate.py
eratos/constants.py
eratos/creds.py
eratos/data.py
eratos/data_old.py
eratos/dataversion.py
eratos/ern.py
eratos/errors.py
eratos/ext.py
eratos/gsdata.py
eratos/gsdata_old.py
eratos/helpers.py
eratos/operator.py
eratos/policy.py
eratos/resource.py
eratos/search.py
eratos/util.py
eratos/dsutil/__init__.py
eratos/dsutil/hashtree.py
eratos/dsutil/manifest.py
eratos/dsutil/netcdf.py
eratos/oapi/__init__.py
eratos/oapi/adapter.py
eratos/oapi/block.py
eratos/oapi/climate.py
eratos/oapi/collection.py
eratos/oapi/creds.py
eratos/oapi/data.py
eratos/oapi/errors.py
eratos/oapi/gsdata.py
eratos/oapi/helpers.py
eratos/oapi/job.py
eratos/oapi/node.py
eratos/oapi/nodelist.py
eratos/oapi/nodetask.py
eratos/oapi/operator.py
eratos/oapi/policy.py
eratos/oapi/resource.py
eratos/oapi/search.py
eratos/oapi/tpsi_block.py
eratos/oapi/util.py
eratos_sdk-0.20.0.dist-info/METADATA
eratos_sdk-0.20.0.dist-info/WHEEL
eratos_sdk-0.20.0.dist-info/licenses/LICENSE
eratos_sdk-0.20.0.dist-info/RECORD
