Metadata-Version: 2.4
Name: eratos-sdk
Version: 0.20.0
Summary: Python SDK for interacting with Eratos platform and services
Project-URL: Homepage, https://eratos.com
Author-email: Eratos <support@eratos.com>
Maintainer-email: Eratos <support@eratos.com>
License-File: LICENSE
Classifier: License :: Other/Proprietary License
Classifier: Operating System :: OS Independent
Classifier: Programming Language :: Python :: 3
Requires-Python: >=3.7
Requires-Dist: deepmerge>=0.1.0
Requires-Dist: h5py>=3.0.0
Requires-Dist: netcdf4>=1.5.0
Requires-Dist: numpy>=1.18.0
Requires-Dist: pandas>=1.3.0
Requires-Dist: pyjwt>=2.3.0
Requires-Dist: pyproj>=3.0.1
Requires-Dist: pyyaml>=5.4.1
Requires-Dist: requests-toolbelt>=1.0.0
Requires-Dist: requests>=2.27.0
Requires-Dist: shapely>=1.8.1
Requires-Dist: sortedcontainers>=2.4.0
Requires-Dist: tabulate>=0.8.9
Requires-Dist: urllib3>=1.26.0
Provides-Extra: dev
Requires-Dist: eratos-xarray>=0.1.8; extra == 'dev'
Requires-Dist: pytest; extra == 'dev'
Requires-Dist: pytest-cov; extra == 'dev'
Requires-Dist: python-dotenv; extra == 'dev'
Requires-Dist: responses; extra == 'dev'
Requires-Dist: sphinx; extra == 'dev'
Requires-Dist: xarray; extra == 'dev'
Provides-Extra: full
Requires-Dist: eratos-as-api; extra == 'full'
Requires-Dist: eratos-as-client; extra == 'full'
Requires-Dist: eratos-sensor; extra == 'full'
Requires-Dist: eratos-tdm; extra == 'full'
Requires-Dist: eratos-tds; extra == 'full'
Requires-Dist: eratos-xarray; extra == 'full'
